examples/__init__.py
examples/get_producer_list.py
examples/listener.py
examples/recorder/__init__.py
examples/recorder/simple_recorder.py
gst_signalling/__init__.py
gst_signalling/gst_abstract_role.py
gst_signalling/gst_consumer.py
gst_signalling/gst_listener.py
gst_signalling/gst_producer.py
gst_signalling/gst_signalling.py
gst_signalling/utils.py
gst_signalling-1.1.2.dist-info/licenses/LICENSE
gst_signalling-1.1.2.dist-info/METADATA
gst_signalling-1.1.2.dist-info/WHEEL
gst_signalling-1.1.2.dist-info/entry_points.txt
gst_signalling-1.1.2.dist-info/top_level.txt
gst_signalling-1.1.2.dist-info/zip-safe
gst_signalling-1.1.2.dist-info/RECORD
