Metadata-Version: 2.4
Name: gst-signalling
Version: 1.1.2
Summary: Python implementation of the gstreamer signalling protocol
Home-page: https://github.com/pollen-robotics/gst-signalling-py
Author: Pollen Robotics
Author-email: contact@pollen-robotics.com
License-File: LICENSE
Requires-Dist: numpy<=2.2.5,>=1.24.0
Requires-Dist: pyee<14
Requires-Dist: websockets<16
Requires-Dist: PyGObject<=3.49.0,>=3.42.2
Provides-Extra: dev
Requires-Dist: black==23.10.1; extra == "dev"
Requires-Dist: flake8==6.1.0; extra == "dev"
Requires-Dist: mypy==1.6.1; extra == "dev"
Requires-Dist: isort==5.12.0; extra == "dev"
Requires-Dist: pygobject-stubs==2.10.0; extra == "dev"
Requires-Dist: pytest==7.4.3; extra == "dev"
Requires-Dist: pytest-asyncio==0.24.0a0; extra == "dev"
Requires-Dist: coverage==7.3.2; extra == "dev"
Dynamic: license-file
